{
  "data": [
    {
      "moonrise_ts": 1588236164,
      "wind_cdir": "SW",
      "rh": 71,
      "pres": 991.745,
      "high_temp": 12.1,
      "sunset_ts": 1588274755,
      "ozone": 415.421,
      "moon_phase": 0.528333,
      "wind_gust_spd": 16.8542,
      "snow_depth": 0,
      "clouds": 84,
      "ts": 1588201260,
      "sunrise_ts": 1588221094,
      "app_min_temp": 8.2,
      "wind_spd": 4.95529,
      "pop": 75,
      "wind_cdir_full": "southwest",
      "slp": 994.634,
      "moon_phase_lunation": 0.24,
      "valid_date": "2020-04-30",
      "app_max_temp": 12.1,
      "vis": 0,
      "dewpt": 5.4,
      "snow": 0,
      "uv": 2.57748,
      "weather": {
        "icon": "r04d",
        "code": 520,
        "description": "Light shower rain"
      },
      "wind_dir": 222,
      "max_dhi": null,
      "clouds_hi": 36,
      "precip": 2.71777,
      "low_temp": 7,
      "max_temp": 12.1,
      "moonset_ts": 1588213543,
      "datetime": "2020-04-30",
      "temp": 10.4,
      "min_temp": 8.2,
      "clouds_mid": 58,
      "clouds_low": 59
    },
    {
      "moonrise_ts": 1588326668,
      "wind_cdir": "WSW",
      "rh": 67,
      "pres": 996.127,
      "high_temp": 16.3,
      "sunset_ts": 1588361258,
      "ozone": 395.003,
      "moon_phase": 0.528333,
      "wind_gust_spd": 13.5582,
      "snow_depth": 0,
      "clouds": 49,
      "ts": 1588287660,
      "sunrise_ts": 1588307376,
      "app_min_temp": 3.9,
      "wind_spd": 4.03555,
      "pop": 20,
      "wind_cdir_full": "west-southwest",
      "slp": 999.065,
      "moon_phase_lunation": 0.27,
      "valid_date": "2020-05-01",
      "app_max_temp": 16.3,
      "vis": 0,
      "dewpt": 4.9,
      "snow": 0,
      "uv": 4.9866,
      "weather": {
        "icon": "c03d",
        "code": 803,
        "description": "Broken clouds"
      },
      "wind_dir": 254,
      "max_dhi": null,
      "clouds_hi": 0,
      "precip": 0.277344,
      "low_temp": 6.3,
      "max_temp": 16.3,
      "moonset_ts": 1588299943,
      "datetime": "2020-05-01",
      "temp": 11.3,
      "min_temp": 7,
      "clouds_mid": 21,
      "clouds_low": 34
    },
    {
      "moonrise_ts": 1588417690,
      "wind_cdir": "W",
      "rh": 67,
      "pres": 1005.79,
      "high_temp": 15.9,
      "sunset_ts": 1588447760,
      "ozone": 384.146,
      "moon_phase": 0.641683,
      "wind_gust_spd": 13.1045,
      "snow_depth": 0,
      "clouds": 29,
      "ts": 1588374060,
      "sunrise_ts": 1588393658,
      "app_min_temp": 2.9,
      "wind_spd": 3.26017,
      "pop": 30,
      "wind_cdir_full": "west",
      "slp": 1008.77,
      "moon_phase_lunation": 0.3,
      "valid_date": "2020-05-02",
      "app_max_temp": 15.9,
      "vis": 0,
      "dewpt": 4.6,
      "snow": 0,
      "uv": 4.98205,
      "weather": {
        "icon": "c02d",
        "code": 802,
        "description": "Scattered clouds"
      },
      "wind_dir": 279,
      "max_dhi": null,
      "clouds_hi": 0,
      "precip": 0.460938,
      "low_temp": 7,
      "max_temp": 15.9,
      "moonset_ts": 1588388067,
      "datetime": "2020-05-02",
      "temp": 11.1,
      "min_temp": 6.3,
      "clouds_mid": 13,
      "clouds_low": 24
    },
    {
      "moonrise_ts": 1588509024,
      "wind_cdir": "S",
      "rh": 66,
      "pres": 1013.61,
      "high_temp": 14.3,
      "sunset_ts": 1588534262,
      "ozone": 353.67,
      "moon_phase": 0.749979,
      "wind_gust_spd": 4.12729,
      "snow_depth": 0,
      "clouds": 93,
      "ts": 1588460460,
      "sunrise_ts": 1588479942,
      "app_min_temp": 9.3,
      "wind_spd": 1.9017,
      "pop": 20,
      "wind_cdir_full": "south",
      "slp": 1018.11,
      "moon_phase_lunation": 0.34,
      "valid_date": "2020-05-03",
      "app_max_temp": 14.3,
      "vis": 24.135,
      "dewpt": 5.2,
      "snow": 0,
      "uv": 2.33505,
      "weather": {
        "icon": "c04d",
        "code": 804,
        "description": "Overcast clouds"
      },
      "wind_dir": 184,
      "max_dhi": null,
      "clouds_hi": 76,
      "precip": 0.0625,
      "low_temp": 10.1,
      "max_temp": 14.6,
      "moonset_ts": 1588475886,
      "datetime": "2020-05-03",
      "temp": 11.7,
      "min_temp": 9.3,
      "clouds_mid": 56,
      "clouds_low": 49
    },
    {
      "moonrise_ts": 1588600520,
      "wind_cdir": "SE",
      "rh": 76,
      "pres": 1012.98,
      "high_temp": 20.2,
      "sunset_ts": 1588620764,
      "ozone": 340.163,
      "moon_phase": 0.846171,
      "wind_gust_spd": 6.80129,
      "snow_depth": 0,
      "clouds": 79,
      "ts": 1588546860,
      "sunrise_ts": 1588566228,
      "app_min_temp": 10.1,
      "wind_spd": 1.81461,
      "pop": 45,
      "wind_cdir_full": "southeast",
      "slp": 1017.54,
      "moon_phase_lunation": 0.37,
      "valid_date": "2020-05-04",
      "app_max_temp": 19.6,
      "vis": 23.5451,
      "dewpt": 9.6,
      "snow": 0,
      "uv": 3.91648,
      "weather": {
        "icon": "c04d",
        "code": 804,
        "description": "Overcast clouds"
      },
      "wind_dir": 140,
      "max_dhi": null,
      "clouds_hi": 63,
      "precip": 2.3125,
      "low_temp": 10.4,
      "max_temp": 20.2,
      "moonset_ts": 1588563525,
      "datetime": "2020-05-04",
      "temp": 14,
      "min_temp": 10.1,
      "clouds_mid": 34,
      "clouds_low": 47
    },
    {
      "moonrise_ts": 1588692103,
      "wind_cdir": "E",
      "rh": 71,
      "pres": 1012.78,
      "high_temp": 14.4,
      "sunset_ts": 1588707265,
      "ozone": 344.903,
      "moon_phase": 0.923247,
      "wind_gust_spd": 15.2099,
      "snow_depth": 0,
      "clouds": 95,
      "ts": 1588633260,
      "sunrise_ts": 1588652515,
      "app_min_temp": 12.5,
      "wind_spd": 5.55193,
      "pop": 80,
      "wind_cdir_full": "east",
      "slp": 1017.28,
      "moon_phase_lunation": 0.4,
      "valid_date": "2020-05-05",
      "app_max_temp": 17.4,
      "vis": 22.3306,
      "dewpt": 9.1,
      "snow": 0,
      "uv": 2.32121,
      "weather": {
        "icon": "r04d",
        "code": 520,
        "description": "Light shower rain"
      },
      "wind_dir": 84,
      "max_dhi": null,
      "clouds_hi": 94,
      "precip": 4.6875,
      "low_temp": 12.1,
      "max_temp": 18.4,
      "moonset_ts": 1588651090,
      "datetime": "2020-05-05",
      "temp": 14.5,
      "min_temp": 12.2,
      "clouds_mid": 63,
      "clouds_low": 41
    },
    {
      "moonrise_ts": 1588783757,
      "wind_cdir": "ENE",
      "rh": 77,
      "pres": 1010.37,
      "high_temp": 19,
      "sunset_ts": 1588793765,
      "ozone": 361.419,
      "moon_phase": 0.975222,
      "wind_gust_spd": 9.90957,
      "snow_depth": 0,
      "clouds": 99,
      "ts": 1588719660,
      "sunrise_ts": 1588738803,
      "app_min_temp": 12.1,
      "wind_spd": 3.80196,
      "pop": 45,
      "wind_cdir_full": "east-northeast",
      "slp": 1014.92,
      "moon_phase_lunation": 0.44,
      "valid_date": "2020-05-06",
      "app_max_temp": 14.3,
      "vis": 22.9016,
      "dewpt": 9.3,
      "snow": 0,
      "uv": 2.32719,
      "weather": {
        "icon": "c04d",
        "code": 804,
        "description": "Overcast clouds"
      },
      "wind_dir": 60,
      "max_dhi": null,
      "clouds_hi": 19,
      "precip": 0.75,
      "low_temp": 11.1,
      "max_temp": 14.4,
      "moonset_ts": 1588738678,
      "datetime": "2020-05-06",
      "temp": 13.2,
      "min_temp": 11.7,
      "clouds_mid": 4,
      "clouds_low": 98
    },
    {
      "moonrise_ts": 1588875472,
      "wind_cdir": "NE",
      "rh": 69,
      "pres": 1010.02,
      "high_temp": 19.2,
      "sunset_ts": 1588880266,
      "ozone": 366.669,
      "moon_phase": 0.998138,
      "wind_gust_spd": 6.30799,
      "snow_depth": 0,
      "clouds": 82,
      "ts": 1588806060,
      "sunrise_ts": 1588825093,
      "app_min_temp": 11.1,
      "wind_spd": 2.46556,
      "pop": 20,
      "wind_cdir_full": "northeast",
      "slp": 1014.57,
      "moon_phase_lunation": 0.47,
      "valid_date": "2020-05-07",
      "app_max_temp": 18.3,
      "vis": 24.135,
      "dewpt": 9,
      "snow": 0,
      "uv": 3.21867,
      "weather": {
        "icon": "c04d",
        "code": 804,
        "description": "Overcast clouds"
      },
      "wind_dir": 47,
      "max_dhi": null,
      "clouds_hi": 41,
      "precip": 0.25,
      "low_temp": 11.2,
      "max_temp": 19.8,
      "moonset_ts": 1588826392,
      "datetime": "2020-05-07",
      "temp": 14.8,
      "min_temp": 10.5,
      "clouds_mid": 32,
      "clouds_low": 66
    },
    {
      "moonrise_ts": 1588967195,
      "wind_cdir": "NE",
      "rh": 68,
      "pres": 1009.16,
      "high_temp": 15,
      "sunset_ts": 1588966765,
      "ozone": 372.297,
      "moon_phase": 0.990738,
      "wind_gust_spd": 4.40099,
      "snow_depth": 0,
      "clouds": 89,
      "ts": 1588892460,
      "sunrise_ts": 1588911385,
      "app_min_temp": 11.2,
      "wind_spd": 2.3404,
      "pop": 85,
      "wind_cdir_full": "northeast",
      "slp": 1013.77,
      "moon_phase_lunation": 0.51,
      "valid_date": "2020-05-08",
      "app_max_temp": 18.5,
      "vis": 20.2995,
      "dewpt": 8.8,
      "snow": 0,
      "uv": 2.71555,
      "weather": {
        "icon": "r01d",
        "code": 500,
        "description": "Light rain"
      },
      "wind_dir": 42,
      "max_dhi": null,
      "clouds_hi": 37,
      "precip": 6.125,
      "low_temp": 11.5,
      "max_temp": 19.3,
      "moonset_ts": 1588914354,
      "datetime": "2020-05-08",
      "temp": 15,
      "min_temp": 10.7,
      "clouds_mid": 72,
      "clouds_low": 33
    },
    {
      "moonrise_ts": 1589058773,
      "wind_cdir": "NNE",
      "rh": 72,
      "pres": 1008.54,
      "high_temp": 10.7,
      "sunset_ts": 1589053264,
      "ozone": 382.816,
      "moon_phase": 0.954572,
      "wind_gust_spd": 8.51353,
      "snow_depth": 0,
      "clouds": 97,
      "ts": 1588978860,
      "sunrise_ts": 1588997678,
      "app_min_temp": 10.7,
      "wind_spd": 3.63372,
      "pop": 80,
      "wind_cdir_full": "north-northeast",
      "slp": 1013.04,
      "moon_phase_lunation": 0.54,
      "valid_date": "2020-05-09",
      "app_max_temp": 14.5,
      "vis": 22.4136,
      "dewpt": 7.7,
      "snow": 0,
      "uv": 2.3576,
      "weather": {
        "icon": "r04d",
        "code": 520,
        "description": "Light shower rain"
      },
      "wind_dir": 30,
      "max_dhi": null,
      "clouds_hi": 32,
      "precip": 4.3125,
      "low_temp": 6.2,
      "max_temp": 15.1,
      "moonset_ts": 1589002714,
      "datetime": "2020-05-09",
      "temp": 12.6,
      "min_temp": 9,
      "clouds_mid": 61,
      "clouds_low": 90
    },
    {
      "moonrise_ts": 1589149944,
      "wind_cdir": "NE",
      "rh": 58,
      "pres": 1015.41,
      "high_temp": 9.7,
      "sunset_ts": 1589139762,
      "ozone": 383.088,
      "moon_phase": 0.893536,
      "wind_gust_spd": 8.81507,
      "snow_depth": 0,
      "clouds": 76,
      "ts": 1589065260,
      "sunrise_ts": 1589083973,
      "app_min_temp": 8.9,
      "wind_spd": 5.97612,
      "pop": 20,
      "wind_cdir_full": "northeast",
      "slp": 1020.01,
      "moon_phase_lunation": 0.57,
      "valid_date": "2020-05-10",
      "app_max_temp": 10.6,
      "vis": 24.1349,
      "dewpt": 1.6,
      "snow": 0,
      "uv": 4.69883,
      "weather": {
        "icon": "c04d",
        "code": 804,
        "description": "Overcast clouds"
      },
      "wind_dir": 36,
      "max_dhi": null,
      "clouds_hi": 2,
      "precip": 0.0625,
      "low_temp": 7.5,
      "max_temp": 10.8,
      "moonset_ts": 1589091626,
      "datetime": "2020-05-10",
      "temp": 9.7,
      "min_temp": 6.2,
      "clouds_mid": 0,
      "clouds_low": 76
    },
    {
      "moonrise_ts": 1589154023,
      "wind_cdir": "NE",
      "rh": 57,
      "pres": 1018.02,
      "high_temp": 15.7,
      "sunset_ts": 1589226260,
      "ozone": 382.068,
      "moon_phase": 0.813071,
      "wind_gust_spd": 10.1,
      "snow_depth": 0,
      "clouds": 55,
      "ts": 1589151660,
      "sunrise_ts": 1589170270,
      "app_min_temp": 2.9,
      "wind_spd": 5.52124,
      "pop": 0,
      "wind_cdir_full": "northeast",
      "slp": 1022.2,
      "moon_phase_lunation": 0.61,
      "valid_date": "2020-05-11",
      "app_max_temp": 9.3,
      "vis": 24.1351,
      "dewpt": -0.4,
      "snow": 0,
      "uv": 2.97105,
      "weather": {
        "icon": "c03d",
        "code": 803,
        "description": "Broken clouds"
      },
      "wind_dir": 45,
      "max_dhi": null,
      "clouds_hi": 6,
      "precip": 0,
      "low_temp": 7.1,
      "max_temp": 9.9,
      "moonset_ts": 1589181181,
      "datetime": "2020-05-11",
      "temp": 7.8,
      "min_temp": 6.2,
      "clouds_mid": 0,
      "clouds_low": 50
    },
    {
      "moonrise_ts": 1589243655,
      "wind_cdir": "NE",
      "rh": 62,
      "pres": 1014.14,
      "high_temp": 10.9,
      "sunset_ts": 1589312757,
      "ozone": 377.824,
      "moon_phase": 0.719302,
      "wind_gust_spd": 8.7075,
      "snow_depth": 0,
      "clouds": 64,
      "ts": 1589238060,
      "sunrise_ts": 1589256569,
      "app_min_temp": 3.1,
      "wind_spd": 3.90929,
      "pop": 0,
      "wind_cdir_full": "northeast",
      "slp": 1018.63,
      "moon_phase_lunation": 0.64,
      "valid_date": "2020-05-12",
      "app_max_temp": 10.3,
      "vis": 24.1348,
      "dewpt": 1.4,
      "snow": 0,
      "uv": 2.40278,
      "weather": {
        "icon": "c03d",
        "code": 803,
        "description": "Broken clouds"
      },
      "wind_dir": 35,
      "max_dhi": null,
      "clouds_hi": 0,
      "precip": 0,
      "low_temp": 6.2,
      "max_temp": 11,
      "moonset_ts": 1589271314,
      "datetime": "2020-05-12",
      "temp": 8.4,
      "min_temp": 6,
      "clouds_mid": 0,
      "clouds_low": 64
    },
    {
      "moonrise_ts": 1589332496,
      "wind_cdir": "NNE",
      "rh": 59,
      "pres": 1014.04,
      "high_temp": 10.4,
      "sunset_ts": 1589399253,
      "ozone": 372.66,
      "moon_phase": 0.618212,
      "wind_gust_spd": 4.02104,
      "snow_depth": 0,
      "clouds": 60,
      "ts": 1589324460,
      "sunrise_ts": 1589342869,
      "app_min_temp": 7.5,
      "wind_spd": 1.99772,
      "pop": 20,
      "wind_cdir_full": "north-northeast",
      "slp": 1018.7,
      "moon_phase_lunation": 0.67,
      "valid_date": "2020-05-13",
      "app_max_temp": 9.7,
      "vis": 24.135,
      "dewpt": 0.9,
      "snow": 0,
      "uv": 2.41815,
      "weather": {
        "icon": "c03d",
        "code": 803,
        "description": "Broken clouds"
      },
      "wind_dir": 32,
      "max_dhi": null,
      "clouds_hi": 0,
      "precip": 0.0625,
      "low_temp": 6.4,
      "max_temp": 10.4,
      "moonset_ts": 1589361814,
      "datetime": "2020-05-13",
      "temp": 8.6,
      "min_temp": 6.4,
      "clouds_mid": 0,
      "clouds_low": 60
    },
    {
      "moonrise_ts": 1589420726,
      "wind_cdir": "NNE",
      "rh": 54,
      "pres": 1017.99,
      "high_temp": 15.7,
      "sunset_ts": 1589485748,
      "ozone": 364.002,
      "moon_phase": 0.514968,
      "wind_gust_spd": 3.53994,
      "snow_depth": 0,
      "clouds": 30,
      "ts": 1589410860,
      "sunrise_ts": 1589429172,
      "app_min_temp": 7.5,
      "wind_spd": 2.10497,
      "pop": 10,
      "wind_cdir_full": "north-northeast",
      "slp": 1022.74,
      "moon_phase_lunation": 0.71,
      "valid_date": "2020-05-14",
      "app_max_temp": 15.7,
      "vis": 24.1348,
      "dewpt": 1.6,
      "snow": 0,
      "uv": 7.53514,
      "weather": {
        "icon": "c02d",
        "code": 802,
        "description": "Scattered clouds"
      },
      "wind_dir": 18,
      "max_dhi": null,
      "clouds_hi": 0,
      "precip": 0.125,
      "low_temp": 7.1,
      "max_temp": 15.7,
      "moonset_ts": 1589452451,
      "datetime": "2020-05-14",
      "temp": 11.6,
      "min_temp": 7.1,
      "clouds_mid": 0,
      "clouds_low": 30
    },
    {
      "moonrise_ts": 1589507126,
      "wind_cdir": "NE",
      "rh": 52,
      "pres": 1020.6,
      "high_temp": 10.8,
      "sunset_ts": 1589572242,
      "ozone": 367.403,
      "moon_phase": 0.413666,
      "wind_gust_spd": 9.00555,
      "snow_depth": 0,
      "clouds": 54,
      "ts": 1589497260,
      "sunrise_ts": 1589515476,
      "app_min_temp": 3.9,
      "wind_spd": 5.20767,
      "pop": 0,
      "wind_cdir_full": "northeast",
      "slp": 1025,
      "moon_phase_lunation": 0.74,
      "valid_date": "2020-05-15",
      "app_max_temp": 10.9,
      "vis": 24.1348,
      "dewpt": -0.4,
      "snow": 0,
      "uv": 4.93652,
      "weather": {
        "icon": "c03d",
        "code": 803,
        "description": "Broken clouds"
      },
      "wind_dir": 42,
      "max_dhi": null,
      "clouds_hi": 6,
      "precip": 0,
      "low_temp": 5.9,
      "max_temp": 10.9,
      "moonset_ts": 1589543070,
      "datetime": "2020-05-15",
      "temp": 9,
      "min_temp": 5.9,
      "clouds_mid": 0,
      "clouds_low": 50
    }
  ],
  "city_name": "London",
  "lon": -0.13,
  "timezone": "Europe/London",
  "lat": 51.51,
  "country_code": "GB",
  "state_code": "ENG"
}
